{
  "title": "jan Poki li kalama wawa!",
  "description": "jan Koto Itoli li meli pi tomo sona sewi. ona li kama sona kalama e ilo kalama linja tan ni: ona li wile lon kulupu jan pi kalama musi. taso, ona li pilin monsuta tan jan la, ona li poka ala tawa jan. taso, ken la, wile ona li ken kama lon tan ni: ona li kama sona e jan Isiki Nisika. jan Nisika li jan pi ilo kalama supa, li alasa e jan sin pi ilo kalama linja tawa kulupu kalama ona.",
  "artist": "jan Amasi Aki",
  "author": "jan Amasi Aki",
  "cover": "https://dl.dropboxusercontent.com/scl/fi/8njia7edsum89uf712lza/.png?rlkey=z3jaeohjwepjsqjvy5l5x0dk7&st=ykaxt1kj&dl=0",
  "chapters": {
    "0": {
      "title": "lipu open pi kulupu lipu nanpa wan",
      "volume": "1",
      "last_updated": "1777269099",
      "groups": {
        "": [
          "https://dl.dropboxusercontent.com/scl/fi/6ffbopnxkabyztqhnzrxf/1.png?rlkey=tjsd3kmybzisscufzq3u5bcmg&st=jfott9oi&dl=0",
          "https://dl.dropboxusercontent.com/scl/fi/3707x2as2hoyvw8zwfhhi/2.png?rlkey=eptbadmgg9662xhw3f3hbvt2z&st=xgjwhvsg&dl=0",
          "https://dl.dropboxusercontent.com/scl/fi/umillxhbuqers3em52h39/3.png?rlkey=88darwnyhcscd2tnbjzpf33a1&st=v7lk5kjz&dl=0",
          "https://dl.dropboxusercontent.com/scl/fi/un1i78dc889e9jf8r7yql/4.png?rlkey=4kfj9gcte6o2tkfzs47y2anav&st=0cz48tba&dl=0",
          "https://dl.dropboxusercontent.com/scl/fi/6ra1snakw9zdkzv40f3ez/5.png?rlkey=sdheuqy0mw2qt8wtwypixm11o&st=5frsrv8v&dl=0",
          "https://dl.dropboxusercontent.com/scl/fi/ug8e2onerlvkbjxg2mj5a/6.png?rlkey=rwdfy44bcziaw81co4vmsussa&st=unw5ci0p&dl=0",
          "https://dl.dropboxusercontent.com/scl/fi/ugdnqfot22fhlwkvqkmen/7.jpg?rlkey=ol0ezpklkftg2oqdidpn6z2of&st=mzqjc6pl&dl=0"
        ]
      }
    },
    "1": {
      "title": "lipu nanpa wan",
      "volume": "1",
      "last_updated": "1777270213",
      "groups": {
        "": [
          "https://dl.dropboxusercontent.com/scl/fi/sht9d2hd1mi3zokksgyit/1.png?rlkey=i6dstwmatyw3tx7psdkdtcima&st=0i9wml1x&dl=0",
          "https://dl.dropboxusercontent.com/scl/fi/rmmt4dk6odo783j6nxida/2.png?rlkey=6iph9bbn5jrhx9iwerdy4epbz&st=6wf22gbq&dl=0",
          "https://dl.dropboxusercontent.com/scl/fi/bywj412bxv30rzta7oxx1/3.png?rlkey=9tup7zzk4rwzsaphhivb6ws35&st=v1u4qmcs&dl=0",
          "https://dl.dropboxusercontent.com/scl/fi/7dqgrdmdazqzaowthawdd/4.png?rlkey=15clnsaexn2s1udt9v2x5vutj&st=gh609aip&dl=0",
          "https://dl.dropboxusercontent.com/scl/fi/2zyv4knmenwg0c0ef4fil/5.png?rlkey=t48xk7s5ljgct31ffalveubza&st=gs2vp6b2&dl=0",
          "https://dl.dropboxusercontent.com/scl/fi/a0cjjrdjn3bxz82mpl5rj/6.png?rlkey=w8sho91bxa73rp515wtmibux1&st=hgzo47td&dl=0",
          "https://dl.dropboxusercontent.com/scl/fi/bfa0hoopv9mynnnhc1jve/7.png?rlkey=3w96h4lg2v4yj6ymrpcjbmuu2&st=3uphru3e&dl=0",
          "https://dl.dropboxusercontent.com/scl/fi/a3nky1eviapus9difup0m/8.png?rlkey=yxhbra5plkkozovvdbieeg85o&st=add0rdyg&dl=0",
          "https://dl.dropboxusercontent.com/scl/fi/l0s130e116oebkev2v4de/9.png?rlkey=rc9k9yiyxr5sskyh5siax7lda&st=09tmoyts&dl=0",
          "https://dl.dropboxusercontent.com/scl/fi/917zvrnqrk3xmzmg3lxp4/10.png?rlkey=s6pptz9lv54hoplwp5r6c0f0s&st=rantiinu&dl=0"
        ]
      }
    },
    "2": {
      "title": "lipu nanpa tu",
      "volume": "1",
      "last_updated": "1777271256",
      "groups": {
        "": [
          "https://dl.dropboxusercontent.com/scl/fi/ammd1f6lxsbtmu0n2jcn2/1.png?rlkey=0bs73rokkui3kanhesrinw35x&st=odzz4r0w&dl=0",
          "https://dl.dropboxusercontent.com/scl/fi/a8hs5qjfiorztvw161zns/2.png?rlkey=8pigqwo7lyw019ht7gqeqwhea&st=fmjrsee9&dl=0",
          "https://dl.dropboxusercontent.com/scl/fi/5yakxgto5yv51p3p01u12/3.png?rlkey=2cipfaaqw57gzrwhggjevwaw8&st=96e9cg98&dl=0",
          "https://dl.dropboxusercontent.com/scl/fi/oqgj4tji4ya6vs2bq5snz/4.png?rlkey=y9r17drjohdb7uimbeoqddytt&st=m5hash5r&dl=0",
          "https://dl.dropboxusercontent.com/scl/fi/tinov8rurx37wm6yvw2cy/5.png?rlkey=4f8461sda5c2udyis0inj8ok3&st=qyhvaypq&dl=0",
          "https://dl.dropboxusercontent.com/scl/fi/l7ciuy892pu53wo7k99ra/6.png?rlkey=gki4tig41189z0zb295n1sc7s&st=m5d5k7li&dl=0",
          "https://dl.dropboxusercontent.com/scl/fi/zmtmk2zjnc2i0enkcttc2/7.png?rlkey=82quasftbn80gnrinw39qasi8&st=kecc86rz&dl=0",
          "https://dl.dropboxusercontent.com/scl/fi/7hs480vwx4vpw2s0qfzpi/8.png?rlkey=1fm3bj2zd92abtg6vmh3am2eh&st=7jtftrqk&dl=0",
          "https://dl.dropboxusercontent.com/scl/fi/fvxq3f1tnd9yyljw0901u/TL-NOTES.png?rlkey=lucxu1mypo0vydu5x1m4e0r7d&st=qv4iqrax&dl=0"
        ]
      }
    },
    "3": {
      "title": "lipu nanpa tu wan",
      "volume": "1",
      "last_updated": "1777271287",
      "groups": {
        "": [
          "https://dl.dropboxusercontent.com/scl/fi/jt6a69x568y0hwgdzx375/1.jpg?rlkey=xmv805wmwpcl3fy1v8rmf2lju&st=6ku36dcj&dl=0",
          "https://dl.dropboxusercontent.com/scl/fi/7rft453xk6m7ix26jf207/2.png?rlkey=eos1hc2eez5bj1aad5pz99djh&st=amr0lt3q&dl=0",
          "https://dl.dropboxusercontent.com/scl/fi/ssl22w1j1ewthai5xvlck/3.png?rlkey=yduhbn9vmybxid15m98b5jk92&st=myqa7lzl&dl=0",
          "https://dl.dropboxusercontent.com/scl/fi/c58s7j4si3x9pjjscy00a/4.png?rlkey=vnnp7qzosjtn23o95xme1jl17&st=m0nlg93y&dl=0",
          "https://dl.dropboxusercontent.com/scl/fi/804a64um3ivfmvrpm40wq/5.png?rlkey=i0h81jysp8b51uydtcxkp3j44&st=sd1iqua6&dl=0",
          "https://dl.dropboxusercontent.com/scl/fi/joyqku6msuvdlhyrpkk17/6.png?rlkey=jbhc8rtq57366ku9jc8i0zb13&st=9dhh0uc2&dl=0",
          "https://dl.dropboxusercontent.com/scl/fi/phequv15vq73q43puzaey/7.png?rlkey=vrt08f1pstlew9hz40cju5k2r&st=3o2x1nvs&dl=0",
          "https://dl.dropboxusercontent.com/scl/fi/n58w7x022vdrvz9t2brv2/8.png?rlkey=q48u2sa0sua7cmow1pu9pia4j&st=yevxk49i&dl=0"
        ]
      }
    },
    "4": {
      "title": "lipu nanpa tu tu",
      "volume": "1",
      "last_updated": "1777271477",
      "groups": {
        "": [
          "https://dl.dropboxusercontent.com/scl/fi/djimse3oqmyx8xox3hmre/1.png?rlkey=erlt601cus57xru4b7ij5m0q3&st=oro1owkl&dl=0",
          "https://dl.dropboxusercontent.com/scl/fi/ix7za62w67z68x91j278v/2.png?rlkey=s0zqh4jeyesysljeeg28vwm7j&st=7d25c9nm&dl=0",
          "https://dl.dropboxusercontent.com/scl/fi/r77qiyja2nccl6dcc5rhr/3.png?rlkey=o7211r664c0itasp22zepyj9t&st=m8277h8e&dl=0",
          "https://dl.dropboxusercontent.com/scl/fi/xxoctg7wnlkiom8u2wuty/4.png?rlkey=r2svll0gpveh6q561ajo9g24b&st=wcdvdv8s&dl=0",
          "https://dl.dropboxusercontent.com/scl/fi/1ctiu88n92srt1x6pqecg/5.png?rlkey=g4xurku2s8nj7ncqvs96ewsll&st=daola5hq&dl=0",
          "https://dl.dropboxusercontent.com/scl/fi/qv995x69twhwzhsrox25e/6.png?rlkey=tci1ddfjdnsw4l202lzjpljf8&st=p1068qx4&dl=0",
          "https://dl.dropboxusercontent.com/scl/fi/cnux5fv58cs7de53x9mmn/7.png?rlkey=lwzc6qb6mf89sh2c69tmpsn85&st=iohjqwxq&dl=0",
          "https://dl.dropboxusercontent.com/scl/fi/dk0ohw1vovslo10krlqyb/8.png?rlkey=vckg0wtybg291u3lbm7scgnk4&st=cen400i5&dl=0",
          "https://dl.dropboxusercontent.com/scl/fi/nudus18x6h66u3attgfst/9.png?rlkey=y58f24o7s2dxn9l16e8gd86yv&st=m9mto840&dl=0",
          "https://dl.dropboxusercontent.com/scl/fi/5d5x2xox7a0rng9exjycr/10.png?rlkey=560byfeib11j9l5h669ktjvwi&st=vry9nxuq&dl=0",
          "https://dl.dropboxusercontent.com/scl/fi/kofxvjqadioqjeok89p7h/TL-NOTES.png?rlkey=y93by8b5gqw3d3imhbq3ifb1a&st=a2hrgon7&dl=0"
        ]
      }
    },
    "5": {
      "title": "lipu nanpa luka",
      "volume": "1",
      "last_updated": "1777271554",
      "groups": {
        "": [
          "https://dl.dropboxusercontent.com/scl/fi/6zn51q3kpx0htlj3ymk87/1.png?rlkey=2shbpkqniyh8v47btn5s1435y&st=aooualm3&dl=0",
          "https://dl.dropboxusercontent.com/scl/fi/20y5lndgjr0w619d7i418/2.png?rlkey=ok5l4j0tw16mtt4g170rv38sn&st=eo43dt5q&dl=0",
          "https://dl.dropboxusercontent.com/scl/fi/dy793igov57ze3ucotmx9/3.png?rlkey=wofl3ckeyyohg3prfshrn1m2i&st=3yxuagr9&dl=0",
          "https://dl.dropboxusercontent.com/scl/fi/85lgny4g397z9cnqewdqf/4.png?rlkey=luuazwyoly4hxkdjjj8gj9aon&st=w2q2a32q&dl=0",
          "https://dl.dropboxusercontent.com/scl/fi/pd6lngwehhmv7mdbz0c0s/5.png?rlkey=9ex8i1l0fflkm7up4nn64hlcy&st=toulqd6n&dl=0",
          "https://dl.dropboxusercontent.com/scl/fi/yroocpj48ufidrtbbempm/6.png?rlkey=79a3rckibccxsw84hbirlddfn&st=54i7q9by&dl=0",
          "https://dl.dropboxusercontent.com/scl/fi/ibb2aqia62kxjfyxfs6ug/7.png?rlkey=v9e4szfaxgv35yp29m42jtcbe&st=hc9egipk&dl=0",
          "https://dl.dropboxusercontent.com/scl/fi/b8zzat21pen973l0kdt8a/8.png?rlkey=ld60b6xah94sa4uot5dttbelt&st=owyy68m6&dl=0"
        ]
      }
    },
    "6": {
      "title": "lipu nanpa luka wan",
      "volume": "1",
      "last_updated": "1777272045",
      "groups": {
        "": [
          "https://dl.dropboxusercontent.com/scl/fi/pz1mivleeosz6x2hr79px/1.png?rlkey=ndwbeinh7x6zwwpjgl0scet2v&st=ohlj18i1&dl=0",
          "https://dl.dropboxusercontent.com/scl/fi/5yymtvn69n6tkpxstcgfa/2.png?rlkey=q682oeyl7x0ilsnq9jhbj5731&st=beckmpk5&dl=0",
          "https://dl.dropboxusercontent.com/scl/fi/06qil46c75r736y07lmke/3.png?rlkey=pkcyii45mwik1zc6vylt8w2nn&st=pn8vxfs8&dl=0",
          "https://dl.dropboxusercontent.com/scl/fi/4b8ni6mahrq5wz0t0w125/4.png?rlkey=g2qjj95cb8jyuy1g5bwjkll86&st=tgc0si17&dl=0",
          "https://dl.dropboxusercontent.com/scl/fi/ijlug6yek8pxbc8wqx5gz/5.png?rlkey=1krbxp95n12la1j7v617hgnf3&st=f3nv0uve&dl=0",
          "https://dl.dropboxusercontent.com/scl/fi/npi7cprni35tfk4406on1/6.png?rlkey=00t5js39zzlb5up0t8b90qr0n&st=7qrk5owi&dl=0",
          "https://dl.dropboxusercontent.com/scl/fi/shu0v414ejq0nvx7x8jpr/7.png?rlkey=vj49c4gx85xnvx94m1cwh9abp&st=3kznx48a&dl=0",
          "https://dl.dropboxusercontent.com/scl/fi/hk47e55oac8g43ncktx5d/8.png?rlkey=k5b0mivcxi6zco4eb6e2cjkae&st=tho15w0q&dl=0"
        ]
      }
    },
    "7": {
      "title": "lipu nanpa luka tu tu",
      "volume": "1",
      "last_updated": "1777272129",
      "groups": {
        "": [
          "https://dl.dropboxusercontent.com/scl/fi/kia74qx7dhvoyym27n6sw/1.png?rlkey=tmnzc4be7asnhejzhujlintp1&st=7v4izayj&dl=0",
          "https://dl.dropboxusercontent.com/scl/fi/olcwrysrwn9seuf8ihwg3/2.png?rlkey=app6ljynyjf0zzt008rix3aoo&st=6yuzge5x&dl=0",
          "https://dl.dropboxusercontent.com/scl/fi/9wfh2fxqdriqvekzho4xs/3.png?rlkey=9no8f081kh7vw91jjcy11yugl&st=gasw1zd5&dl=0",
          "https://dl.dropboxusercontent.com/scl/fi/jw4hhrwv6v0ohh7vaxo3w/4.png?rlkey=hj9kpvsb95gbjip3x1risjv8s&st=vu9s7pk7&dl=0",
          "https://dl.dropboxusercontent.com/scl/fi/bkted7bjt2en37658z998/5.png?rlkey=l10t9uin99g3mgy939miwgb39&st=5d96aj6z&dl=0",
          "https://dl.dropboxusercontent.com/scl/fi/wprmlodd3oulxf2tu7zgq/6.png?rlkey=i9jcjdr00k00j296zilgezj9d&st=jrugclw7&dl=0",
          "https://dl.dropboxusercontent.com/scl/fi/s2rwjsu6uv5aceqi9i2et/7.png?rlkey=6z2f7xs0ib9vyz8m2vmkk1j5u&st=hb6uk87l&dl=0",
          "https://dl.dropboxusercontent.com/scl/fi/g27afkss05xhtd17knvqu/8.png?rlkey=lbgiqkkgpwg22spvhmakpzmxs&st=p878vsso&dl=0",
          "https://dl.dropboxusercontent.com/scl/fi/z1lc6rb6adxcir5isyc9o/9.png?rlkey=2bgc84poxivxvqe69a9c2g9pr&st=z3ravs9s&dl=0",
          "https://dl.dropboxusercontent.com/scl/fi/8hadp8cdg6ps1c5t2d3qo/10.png?rlkey=clasnzkavkybq16lkvs217c6g&st=d27y7w2q&dl=0",
          "https://dl.dropboxusercontent.com/scl/fi/618xxv32fhoqyy0cjt3vc/TL-NOTES.png?rlkey=9i32vr529pmemla59isscz4ct&st=2wj25nh2&dl=0"
        ]
      }
    },
    "8": {
      "title": "lipu nanpa luka tu wan",
      "volume": "1",
      "last_updated": "1777272148",
      "groups": {
        "": [
          "https://dl.dropboxusercontent.com/scl/fi/mfoluw8q5u111mgrc45up/1.png?rlkey=7llhckai4j06kqm7qy3qebkb7&st=dqkb0901&dl=0",
          "https://dl.dropboxusercontent.com/scl/fi/di36u3awihy6lwocijqrq/2.png?rlkey=6rpazpr98up6p6lm4gyi0613v&st=h7ikriur&dl=0",
          "https://dl.dropboxusercontent.com/scl/fi/mo37jvpj65p3kxykueo2g/3.png?rlkey=uhhjztc9u47fkl8pdyrbk36jr&st=qv5fr107&dl=0",
          "https://dl.dropboxusercontent.com/scl/fi/t3tjkc2m2r1n3uuruj03i/4.png?rlkey=o85stk8ns5j0lpqd4mb78is7m&st=76bml4sh&dl=0",
          "https://dl.dropboxusercontent.com/scl/fi/rwp7ul39rmp007ux11s09/5.png?rlkey=oycq93kpbzkmc36a1iyn5t7hl&st=vpzibolq&dl=0",
          "https://dl.dropboxusercontent.com/scl/fi/m8966l97io1m40myoe9lq/6.png?rlkey=o5dtpo8fh4ngzpddfk09yilit&st=x8yh32if&dl=0",
          "https://dl.dropboxusercontent.com/scl/fi/8xpgj0unfj0wacfg5mahc/7.png?rlkey=rxuimrbk03enoupnsqcxbnad5&st=dxnkx2p5&dl=0",
          "https://dl.dropboxusercontent.com/scl/fi/pxj8awzejtyuplzdz8hma/8.png?rlkey=590urplje4ea5v5qrhtvmkyn3&st=ceafhrhm&dl=0"
        ]
      }
    },
    "9": {
      "title": "lipu nanpa luka tu tu",
      "volume": "1",
      "last_updated": "1777272170",
      "groups": {
        "": [
          "https://dl.dropboxusercontent.com/scl/fi/95jzckd4qli2ld9ulyjx5/1.png?rlkey=3k6f1c2jbuf7vf3j8r8h8z2u3&st=b4a4hzeq&dl=0",
          "https://dl.dropboxusercontent.com/scl/fi/60nfp777elnv4173eadaf/2.png?rlkey=xm9cnufbyem5mw53yigbfoq0v&st=h1x22jxb&dl=0",
          "https://dl.dropboxusercontent.com/scl/fi/c2a0ka10mr38bqn81ywps/3.png?rlkey=nseuh5xsu5laa4n0w3ofp6d7z&st=3gtz770h&dl=0",
          "https://dl.dropboxusercontent.com/scl/fi/ozlnmoqym64amvs5wqjnl/4.png?rlkey=vks83suy5722vmj3th5ycaf14&st=mbh4s3gt&dl=0",
          "https://dl.dropboxusercontent.com/scl/fi/k28efeean21hzzl1wzsr5/5.png?rlkey=b75pf0zlnq281qd7vx8x6cius&st=rjj3afal&dl=0",
          "https://dl.dropboxusercontent.com/scl/fi/0v6ucrbil8rq99e9njnmc/6.png?rlkey=mzxsh6vrlayxy5o1e0gnwn8zd&st=blkz4ecm&dl=0",
          "https://dl.dropboxusercontent.com/scl/fi/3athrrz1sz6ol58h7rtix/7.png?rlkey=5qjqdoj9rgkrmfq91jqe2fr74&st=ltkcgu5n&dl=0",
          "https://dl.dropboxusercontent.com/scl/fi/85tedeh6f3jlfghzp4ayh/8.png?rlkey=y2f730l8qls0yiitrsm5ubz1v&st=p6n3fx4o&dl=0"
        ]
      }
    },
    "10": {
      "title": "lipu nanpa luka luka",
      "volume": "1",
      "last_updated": "1777272190",
      "groups": {
        "": [
          "https://dl.dropboxusercontent.com/scl/fi/tuhqjlhkq9mj5tknt5qq2/1.png?rlkey=zh6wt7sbra2oxa9g3uj76u6cg&st=fyuafhjt&dl=0",
          "https://dl.dropboxusercontent.com/scl/fi/5m9s0joeysmi5bqeilvoe/2.png?rlkey=hi292sn6v88ornbzu6eep9spa&st=4px3i1vj&dl=0",
          "https://dl.dropboxusercontent.com/scl/fi/0zzdd7veqjy767c71dky1/3.png?rlkey=b624323vs5thq64jo12gewdrs&st=czkrpzd0&dl=0",
          "https://dl.dropboxusercontent.com/scl/fi/sqlidk8lxzmqr7jmiiwb4/4.png?rlkey=gkhji3mr1sramnbz10jssa7tk&st=tx9bfxfa&dl=0",
          "https://dl.dropboxusercontent.com/scl/fi/pkt2lovyhzvle3x6ecllp/5.png?rlkey=o0pfec02aq2tx59dsb2p92z1g&st=wyhv46jo&dl=0",
          "https://dl.dropboxusercontent.com/scl/fi/pkw6z4tw9p4u8q2tevd4s/6.png?rlkey=4uz4scnzt26ynd8288s72j0kd&st=48f9ter3&dl=0",
          "https://dl.dropboxusercontent.com/scl/fi/9f3auiffevohdleurnfpf/7.png?rlkey=x53glu8longlt05i4lox8kve0&st=g0epglhf&dl=0",
          "https://dl.dropboxusercontent.com/scl/fi/jci4po0adza3jekkv3lhf/8.png?rlkey=hj6s1nlwjoc50ptt7zk4wj2id&st=078w6tlx&dl=0"
        ]
      }
    },
    "11": {
      "title": "lipu nanpa luka luka wan",
      "volume": "1",
      "last_updated": "1777272205",
      "groups": {
        "": [
          "https://dl.dropboxusercontent.com/scl/fi/qwjttv3zwzd3jwo0x1gv5/1.png?rlkey=ymuspgla4vvfxzvqq0iz2cqm0&st=7rmgni8q&dl=0",
          "https://dl.dropboxusercontent.com/scl/fi/9gc13afwbzk8sic0i4d31/2.png?rlkey=icy1raz7ee6c85djfqgroyo90&st=yxmts3qh&dl=0",
          "https://dl.dropboxusercontent.com/scl/fi/75643wmeesohvpz1uqf4q/3.png?rlkey=9jtchiacya2vaxbls0qx4lgsx&st=owinjuri&dl=0",
          "https://dl.dropboxusercontent.com/scl/fi/1k8col5qkv3b7zse54w7d/4.png?rlkey=406wmnzyeby3to1gxxadi1yxb&st=oh2trdx6&dl=0",
          "https://dl.dropboxusercontent.com/scl/fi/8t6z478gcayf1t4i2lyyz/5.png?rlkey=h864k2vjjbct9ioyayqy955dg&st=0067ic7n&dl=0",
          "https://dl.dropboxusercontent.com/scl/fi/9d7fih0culg4yy771l4jo/6.png?rlkey=eaaiyqg69gm1t3jacjs4qiv9p&st=rdh1up8s&dl=0",
          "https://dl.dropboxusercontent.com/scl/fi/qc7g1i44mftot4qeoi6vf/7.png?rlkey=6kgf5tw6uqms3ne5789hlj0td&st=kyeuv5yr&dl=0",
          "https://dl.dropboxusercontent.com/scl/fi/aj1pxz3rmxgkc8rk9djac/8.png?rlkey=o57d342x8sug5czm2qxwdzq4z&st=zvy929mt&dl=0"
        ]
      }
    },
    "12": {
      "title": "lipu nanpa luka luka tu",
      "volume": "1",
      "last_updated": "1777272221",
      "groups": {
        "": [
          "https://dl.dropboxusercontent.com/scl/fi/93akk2uisyw3gtfdjdxlw/1.png?rlkey=pu8x9h407jwud4n2rpy6wx19w&st=ufdado24&dl=0",
          "https://dl.dropboxusercontent.com/scl/fi/deawjioiw3fsd81no1gs9/2.png?rlkey=r43mcsma9wge004d6gn487q3f&st=hzkn69k0&dl=0",
          "https://dl.dropboxusercontent.com/scl/fi/wtnkso90dh1yxuiqnkwl7/3.png?rlkey=ncfvq1qlzn74d49olclwk2gcb&st=qpa0jybr&dl=0",
          "https://dl.dropboxusercontent.com/scl/fi/2r0ynj65ti20wken8a0cp/4.png?rlkey=fbh1tgkyvrdn2oaj4trp47t98&st=89v0zlgv&dl=0",
          "https://dl.dropboxusercontent.com/scl/fi/52924vnc6vs1m038ohydj/5.png?rlkey=x1kzsetyr4rezxgcaxcq5z46k&st=c79rmqyi&dl=0",
          "https://dl.dropboxusercontent.com/scl/fi/6tfh1eexj3s3z66ra4doo/6.png?rlkey=j6wbxw0ybufoytkxf9js6jgja&st=snsictpi&dl=0",
          "https://dl.dropboxusercontent.com/scl/fi/2f5fvowzq61im9ohe95qm/7.png?rlkey=uw4zp2h0hqxhyw9mphwg6u4nq&st=qqttkf9w&dl=0",
          "https://dl.dropboxusercontent.com/scl/fi/r5p6yrdluoi0b2agkacke/8.png?rlkey=vgnjewj6pjtcflk65uiuo7i54&st=szrl7snv&dl=0"
        ]
      }
    },
    "13": {
      "title": "lipu nanpa luka luka tu wan",
      "volume": "1",
      "last_updated": "1777272241",
      "groups": {
        "": [
          "https://dl.dropboxusercontent.com/scl/fi/jtw4ssx2twvzsoaa2dwjp/1.png?rlkey=r8j8mj0mapblor6a31xm4glhc&st=wbw6q55l&dl=0",
          "https://dl.dropboxusercontent.com/scl/fi/e8hxrdycerkdf0dvjolc9/2.png?rlkey=exzo8spla6cetahl3z31rb3sx&st=7xxqalts&dl=0",
          "https://dl.dropboxusercontent.com/scl/fi/c2s4uc5rr8b6zudjrr02a/3.png?rlkey=11cvkp5ho9j5hdiex4hq8i02r&st=gqcckpmw&dl=0",
          "https://dl.dropboxusercontent.com/scl/fi/6kgri2vvkecdyr1x2hzah/4.png?rlkey=2vi6ezgjr1jbmqhooharqoa9w&st=dt8zb5f0&dl=0",
          "https://dl.dropboxusercontent.com/scl/fi/t5vm1yxnxvppx84u0gcqf/5.png?rlkey=6f0nfq50bgbcn7ix4jmog5ly3&st=yl51qzib&dl=0",
          "https://dl.dropboxusercontent.com/scl/fi/i5m8c2ja4hkcanoes1v4w/6.png?rlkey=qy3ccb6341mzmsule7fn7ya2g&st=492jlo4k&dl=0",
          "https://dl.dropboxusercontent.com/scl/fi/0zpqfc78kc60x2vesifxq/7.png?rlkey=81kq62bctc7es988vr6lkfguv&st=rmal08v3&dl=0",
          "https://dl.dropboxusercontent.com/scl/fi/77kdyox8wn7duu9z2yorr/8.png?rlkey=wrcvp76mxcc6fnpttwa84d9r3&st=94ya12kb&dl=0"
        ]
      }
    },
    "14": {
      "title": "lipu nanpa luka luka tu tu",
      "volume": "2",
      "last_updated": "1777272627",
      "groups": {
        "": [
          "https://dl.dropboxusercontent.com/scl/fi/zdkphpnfs3pnqjkekevy8/1.png?rlkey=cd570cuqquh3ykgkdw2afnjoo&st=mte5b9zg&dl=0",
          "https://dl.dropboxusercontent.com/scl/fi/jdy9ugsej53ndjsynwlql/2.png?rlkey=n8l3exufzacdadje1hgx1ha44&st=ejsqiyrj&dl=0",
          "https://dl.dropboxusercontent.com/scl/fi/bb2esk3rz657vgpu8rdgu/3.png?rlkey=cjelhvujgdz09zeruq6d0nnue&st=5hs4zuov&dl=0",
          "https://dl.dropboxusercontent.com/scl/fi/gnujihvh615us77yi5ct3/4.png?rlkey=4gcvomv5tedty710m6l1sl9ds&st=jry168wm&dl=0",
          "https://dl.dropboxusercontent.com/scl/fi/qnybs5fv43n5vse4apv1e/5.png?rlkey=bwkmiqeu9pfbsvgolg2do1u2v&st=ecg0iqsi&dl=0",
          "https://dl.dropboxusercontent.com/scl/fi/dt9fd0cij82tgxcdp2fda/6.png?rlkey=z5whx6z7rqbu5900xodgsm0f7&st=jh4ohh76&dl=0",
          "https://dl.dropboxusercontent.com/scl/fi/efannjqosblz9c4l08fa1/7.png?rlkey=eldfyjfu6uycmwunn2y5wo2rv&st=3k8nden4&dl=0",
          "https://dl.dropboxusercontent.com/scl/fi/1wdlupzgacd2uficjh7ik/8.png?rlkey=sdismpd14xpym9vp27l40i09o&st=oqgoiv0t&dl=0"
        ]
      }
    },
    "15": {
      "title": "lipu nanpa luka luka luka",
      "volume": "2",
      "last_updated": "1777272640",
      "groups": {
        "": [
          "https://dl.dropboxusercontent.com/scl/fi/rzgd59h9zd1wgh745nkqb/1.png?rlkey=i50qnv8c4zkzn5549zvcl8m3o&st=ch905828&dl=0",
          "https://dl.dropboxusercontent.com/scl/fi/2c8mk2nqgw1u5bkmn6nzd/2.png?rlkey=3cvmfdn4tv7xt4wwzlqz6x56z&st=8iz79mi3&dl=0",
          "https://dl.dropboxusercontent.com/scl/fi/ezl5y07ovt4kv9dp26xrk/3.png?rlkey=u9so872b4mr9e7pl0tchp72vr&st=10qvtvcy&dl=0",
          "https://dl.dropboxusercontent.com/scl/fi/sv3gajuq4je4d4u8q2niv/4.png?rlkey=wuz9rpxjen0tnz2mpp3kzf6lh&st=zqwerbi3&dl=0",
          "https://dl.dropboxusercontent.com/scl/fi/7b6xc9uu6kb6uz528fqmd/5.png?rlkey=7zq5dc27fvqsrjlmx8423tm9i&st=jxta7ucw&dl=0",
          "https://dl.dropboxusercontent.com/scl/fi/w0yh8gnfe0bgvndj4em8x/6.png?rlkey=4arhp7180x099lyoch98pps4v&st=hvkzn0sb&dl=0",
          "https://dl.dropboxusercontent.com/scl/fi/tyg9n3mk7720yf9tikxay/7.png?rlkey=vbbv3ou6dx0uzajuqv09w2xi5&st=w1jr6wet&dl=0",
          "https://dl.dropboxusercontent.com/scl/fi/vpy06hecq4ew7yjafd07u/8.png?rlkey=kqug90vh1t6yvvgs27bom0pyk&st=an3yt11c&dl=0"
        ]
      }
    },
    "16": {
      "title": "lipu nanpa luka luka luka wan",
      "volume": "2",
      "last_updated": "1777272670",
      "groups": {
        "": [
          "https://dl.dropboxusercontent.com/scl/fi/27xi8bbdrptey89ulqw4y/1.png?rlkey=rftedu3z4mwfp0lfg9coxt146&st=jbkd1b6p&dl=0",
          "https://dl.dropboxusercontent.com/scl/fi/w4yx9gm7wrxfqfg7quqbl/2.png?rlkey=80je1k7qfrzxhxohdi9uwajdl&st=x7lv3tu5&dl=0",
          "https://dl.dropboxusercontent.com/scl/fi/0wuvgaj5vo769ac6k0rhz/3.png?rlkey=yo1dnzgy1l7f1ttlgxpp7qoj8&st=or7ymf30&dl=0",
          "https://dl.dropboxusercontent.com/scl/fi/rmwlz5dubke7aeys54wiw/4.png?rlkey=bw0j70atcg7qw5r7zpyxdhf2j&st=71k98kk1&dl=0",
          "https://dl.dropboxusercontent.com/scl/fi/pb9v3ogr8iaurqhzh81ji/5.png?rlkey=96n53dbyz8pqjizhjyjnjvrx3&st=q36euw2v&dl=0",
          "https://dl.dropboxusercontent.com/scl/fi/eqn2oso3c9q4ymzlt8un8/6.png?rlkey=06revwtlod1p8vdq2h9pfrv4m&st=nwifd1nt&dl=0",
          "https://dl.dropboxusercontent.com/scl/fi/n63iymlxaxb4575z6h115/7.png?rlkey=ki7mp2d0hr1v4kngpwcgeiw71&st=1ekqtnf8&dl=0",
          "https://dl.dropboxusercontent.com/scl/fi/l1kvyl1ikvee9f5w577tz/8.png?rlkey=qyxl8s8swf9abpvds44i8vevh&st=kxdc7md3&dl=0"
        ]
      }
    },
    "17": {
      "title": "lipu nanpa luka luka luka tu",
      "volume": "2",
      "last_updated": "1777272685",
      "groups": {
        "": [
          "https://dl.dropboxusercontent.com/scl/fi/x5qykh06wuzphm5ii2qca/1.png?rlkey=nov1zwmhzoxu5wzo6geilnn6t&st=we93vnm0&dl=0",
          "https://dl.dropboxusercontent.com/scl/fi/3u8wgw6y3847o6g298i96/2.png?rlkey=xp76y1t9mrjhbv840slcovxqz&st=b08a5yaj&dl=0",
          "https://dl.dropboxusercontent.com/scl/fi/qpd0igo41cwwrrzfhl663/3.png?rlkey=xvkr8hussravo5y0sm7z30cb8&st=m1y3kld5&dl=0",
          "https://dl.dropboxusercontent.com/scl/fi/svbsuyuh1gnzbkjaraoek/4.png?rlkey=u4981n7cbh74vsd62x1pc4103&st=7t6idbvs&dl=0",
          "https://dl.dropboxusercontent.com/scl/fi/l28ieo7853h4o9k7g0q0p/5.png?rlkey=iofvwl86jmwh6kozqqavxdhrp&st=rw0y6p61&dl=0",
          "https://dl.dropboxusercontent.com/scl/fi/lz9d3qwanxpqgq30puttz/6.png?rlkey=wtfe7hs2ytcjerhxtcvini2vg&st=f1ofnm3g&dl=0",
          "https://dl.dropboxusercontent.com/scl/fi/lleuysa33cqxjllq1q9xz/7.png?rlkey=tev3byml3tbx2dri3uo81s59f&st=hb3che6a&dl=0",
          "https://dl.dropboxusercontent.com/scl/fi/x4vgf21qn8iyi3f8qr7nj/8.png?rlkey=nvkdx64mh1lqr1aqfm74zgqtk&st=dixe5tzb&dl=0",
          "https://dl.dropboxusercontent.com/scl/fi/3uncb0ip70t6xcm8qd3xd/9.png?rlkey=2pf2ztsvfa70dkaz9uh2ta518&st=dxgi8b9h&dl=0",
          "https://dl.dropboxusercontent.com/scl/fi/3n02tjtnlyvuqilgj0s08/10.png?rlkey=qvx1sk4ubgxf44vxwnt7nafak&st=i3ibg4ob&dl=0"
        ]
      }
    },
    "18": {
      "title": "lipu nanpa luka luka luka tu wan",
      "volume": "2",
      "last_updated": "1777272708",
      "groups": {
        "": [
          "https://dl.dropboxusercontent.com/scl/fi/83262y5lmkwex0suj35nm/1.png?rlkey=a8wytavngclkpju8o4u7b4lcp&st=i3k5hj03&dl=0",
          "https://dl.dropboxusercontent.com/scl/fi/ki5irfm83coy0gm3c6fjq/2.png?rlkey=vydu11ferjf2ybyw19xxf3mco&st=u2rxi4eo&dl=0",
          "https://dl.dropboxusercontent.com/scl/fi/epmcznk62um9cc1z9msnz/3.png?rlkey=xh9qum8m79qjggjso8929j5wp&st=4u60xly2&dl=0",
          "https://dl.dropboxusercontent.com/scl/fi/194yvvw0psl8e1iiht7w7/4.png?rlkey=cm1wwbrek6lnnl8k8155v77ta&st=rbzg908a&dl=0",
          "https://dl.dropboxusercontent.com/scl/fi/ur41w4iu0tuvtx55so5xh/5.png?rlkey=vwrjm6rldl9r6yrytav0kneua&st=hgln73mo&dl=0",
          "https://dl.dropboxusercontent.com/scl/fi/vqc8hkdefno0svt1erru7/6.png?rlkey=xfobokrt9z2owjxbugqxno9ic&st=d4bfzgv5&dl=0",
          "https://dl.dropboxusercontent.com/scl/fi/8x2t5ydk2xpc61o4p8m47/7.png?rlkey=pdv4xqx0xhej2bg7n6exq19xp&st=t67fj1r2&dl=0",
          "https://dl.dropboxusercontent.com/scl/fi/u1hplgnkzr28gdsnvk4ky/8.png?rlkey=evesw8vqkrwpko5uy8dq668rn&st=hdrwdjrf&dl=0"
        ]
      }
    },
    "19": {
      "title": "lipu nanpa luka luka luka tu tu",
      "volume": "2",
      "last_updated": "1777272722",
      "groups": {
        "": [
          "https://dl.dropboxusercontent.com/scl/fi/krj6ileyl17rcz2lgqbx9/1.png?rlkey=mpdgnuyueona7gce7h28yd1l0&st=w8qw8cii&dl=0",
          "https://dl.dropboxusercontent.com/scl/fi/8qu9v9iqzjut3wnsftws1/2.png?rlkey=7gq1g9qhltcayau6xv489qvp8&st=tokp0rrj&dl=0",
          "https://dl.dropboxusercontent.com/scl/fi/uxxz0wkd9f1gfnx0umos9/3.png?rlkey=8ju18micazrguvwavt9nzpai7&st=kepem3pd&dl=0",
          "https://dl.dropboxusercontent.com/scl/fi/o0llalianmpczykgkorec/4.png?rlkey=t5nu542qsrnj1rtpeir143u89&st=axq1my6k&dl=0",
          "https://dl.dropboxusercontent.com/scl/fi/ogzb7nhtkz2ew1qdwesuj/5.png?rlkey=bg0i1ljevvcjiffm7p3onxr9g&st=dw5fhs1x&dl=0",
          "https://dl.dropboxusercontent.com/scl/fi/6kqy1q6vp7ophsnb2v4qa/6.png?rlkey=nrpj39qgax0ti5n4xbwnygi3a&st=t6if9c3s&dl=0",
          "https://dl.dropboxusercontent.com/scl/fi/ilisc8d83zm0w56ozl49x/7.png?rlkey=mstxuuodc7snpjrbw9r8fl4b9&st=ppt4ls4h&dl=0",
          "https://dl.dropboxusercontent.com/scl/fi/oxw0c2zotz2chk02kw51k/8.png?rlkey=rrpdj0eurjkkume21qu54cftt&st=7p52lju0&dl=0"
        ]
      }
    },
    "13.5": {
      "title": "lipu namako en sinpin namako",
      "volume": "1",
      "last_updated": "1777272268",
      "groups": {
        "": [
          "https://dl.dropboxusercontent.com/scl/fi/jgj3j76ez16mbjyplpbhf/1.-sitelen-sinpin.png?rlkey=3dgjtr08uchmhrrusp1rxcb6m&st=71w1tp63&dl=0",
          "https://dl.dropboxusercontent.com/scl/fi/35nts6fs4bva64npfzfrm/2.-sitelen-insa.png?rlkey=z6y75fz6bnr2s2jjgxzxfr3sv&st=h1biwfu7&dl=0",
          "https://dl.dropboxusercontent.com/scl/fi/3a0ub2a9bshaf9or5ld76/3.-sitelen-poka-en-sitelen-monsi-en-sitelen-insa.png?rlkey=3kklr7hneliseq0s909kv7l16&st=sj2cjhea&dl=0",
          "https://dl.dropboxusercontent.com/scl/fi/jnrbti3ip8ek46p2x30r0/4.-toki-pi-mama-lipu.png?rlkey=k4bsybszvq3xmh0ga61hc51qb&st=a8eroi8n&dl=0",
          "https://dl.dropboxusercontent.com/scl/fi/6re2dwanlbp4uu03jcbfn/5.-lipu-namako.png?rlkey=8uo9q9lspixolh6pr8fsu0wk1&st=dfh92vb5&dl=0",
          "https://dl.dropboxusercontent.com/scl/fi/iopbdul4elldg4ylbz9ae/6.-sona-lipu.png?rlkey=kypmzdblnrdstdcxwt1dhhh34&st=bvfu8phi&dl=0"
        ]
      }
    },
    "13.9": {
      "title": "lipu open pi kulupu lipu nanpa tu",
      "volume": "2",
      "last_updated": "1777272325",
      "groups": {
        "": [
          "https://dl.dropboxusercontent.com/scl/fi/4ucmk5hgepa8veulp47lt/1.png?rlkey=gq6ipn2z8gry40smhmg6o932q&st=ya1muff3&dl=0",
          "https://dl.dropboxusercontent.com/scl/fi/ryshvdi16lbk7y3aoaqj0/2.png?rlkey=e8yqvic8q6fvjd52sao7epapu&st=1j0s91k8&dl=0",
          "https://dl.dropboxusercontent.com/scl/fi/0pz4andrwjtztbe0ry1fv/3.png?rlkey=lxag2x8bi20z5zwyt7oflwwvv&st=9tlhr3cn&dl=0",
          "https://dl.dropboxusercontent.com/scl/fi/luyss6azmjrqna0h0rp4f/4.png?rlkey=jhrqi5e88lutxy8lkgz5f467x&st=90h411yj&dl=0",
          "https://dl.dropboxusercontent.com/scl/fi/nme9tvy3f7pv8t6s0aps2/5.png?rlkey=u7gegl4m8k56azkcsdo1d0b11&st=9j5bcz6h&dl=0",
          "https://dl.dropboxusercontent.com/scl/fi/wsfqw27qhoh82fbyu0hjl/6.png?rlkey=k56o1xx5puzq5edgspn9r0vl0&st=lcl97hhp&dl=0",
          "https://dl.dropboxusercontent.com/scl/fi/chd6mm2oi0el54eyivbbg/7.png?rlkey=mjuo59wg69wxwtpsz34w8du75&st=2klevdzv&dl=0",
          "https://dl.dropboxusercontent.com/scl/fi/dug41p7hzfpvh7dq23wfp/8.png?rlkey=rlhkkx37sok2s31pvjq2m071l&st=am1ma7qu&dl=0",
          "https://dl.dropboxusercontent.com/scl/fi/xo467wl8xu4x9y5cg7f5o/9.png?rlkey=2w0urobmwdr2qwromes79liip&st=xnx7d6qp&dl=0"
        ]
      }
    }
  }
}